vpncmd/__init__.py
vpncmd/core.py
vpncmd/helper.py
vpncmd/utils.py
vpncmd/__metadata__/DISCLIAIMER.md
vpncmd/__metadata__/LICENSE
vpncmd/__metadata__/README.md
vpncmd/__metadata__/__init__.py
vpncmd/__metadata__/requirements.txt
vpncmd-0.8.0.dist-info/METADATA
vpncmd-0.8.0.dist-info/WHEEL
vpncmd-0.8.0.dist-info/top_level.txt
vpncmd-0.8.0.dist-info/RECORD
