Metadata-Version: 2.1
Name: vpncmd
Version: 0.8.0
Summary: API for Softether VPN (vpncmd) with automatic connection to VPNs provided by VPN Gate.
Home-page: http://code.foxe6.kozow.com/vpncmd/
Author: f̣ộx̣ệ6
Author-email: foxe6@pm.me
License: AGPL-3.0
Project-URL: Sourcecode, http://code.foxe6.kozow.com/vpncmd.zip
Project-URL: Documentation, http://code.foxe6.kozow.com/vpncmd/docs/
Project-URL: Example, http://code.foxe6.kozow.com/vpncmd/test/
Project-URL: Funding, https://paypal.me/foxe6
Project-URL: Say Thanks!, https://saythanks.io/to/foxe6
Keywords: vpn vpngate softether vpncmd cli api rpc cmd commandline command
Platform: UNKNOWN
Classifier: Programming Language :: Python :: 3.9
Classifier: Topic :: Utilities
Classifier: Natural Language :: English
Classifier: Intended Audience :: Developers
Classifier: License :: OSI Approved :: GNU Affero General Public License v3
Classifier: Operating System :: MacOS
Classifier: Operating System :: POSIX
Classifier: Operating System :: Microsoft :: Windows :: Windows 10
Classifier: Development Status :: 5 - Production/Stable
Requires-Python: >=3.5
Requires-Dist: requests (>=0.0.1)
Requires-Dist: lxml (>=0.0.1)
Requires-Dist: netifaces (>=0.0.1)
